mubicryy/__init__.py
mubicryy-0.4.dist-info/LICENSE.txt
mubicryy-0.4.dist-info/METADATA
mubicryy-0.4.dist-info/WHEEL
mubicryy-0.4.dist-info/top_level.txt
mubicryy-0.4.dist-info/RECORD
