Metadata-Version: 2.1
Name: mubicryy
Version: 0.4
Summary: Funcoes usadas no dia a dia
Home-page: 
Author: Fabricio Leal
Author-email: 
License: MIT
Classifier: Development Status :: 5 - Production/Stable
Classifier: Intended Audience :: Education
Classifier: Operating System :: Microsoft :: Windows :: Windows 10
Classifier: License :: OSI Approved :: MIT License
Classifier: Programming Language :: Python :: 3
License-File: LICENSE.txt
